{
  "ep_length_mean": {
    "steps": [
      500
    ],
    "timestamps": [
      "2023-05-19T20:54:01.478102"
    ],
    "values": [
      50.0
    ]
  },
  "episode": {
    "steps": [
      500,
      1000
    ],
    "timestamps": [
      "2023-05-19T20:54:26.032334",
      "2023-05-19T20:54:44.026210"
    ],
    "values": [
      10,
      20
    ]
  },
  "go_explore_return": {
    "steps": [
      250,
      500,
      750,
      250,
      500,
      750
    ],
    "timestamps": [
      "2023-05-19T20:54:21.053079",
      "2023-05-19T20:54:21.054060",
      "2023-05-19T20:54:21.055060",
      "2023-05-19T20:54:44.026210",
      "2023-05-19T20:54:44.026210",
      "2023-05-19T20:54:44.026210"
    ],
    "values": [
      0.0,
      0.0,
      0.0,
      0.0,
      0.0,
      0.0
    ]
  },
  "return_mean": {
    "steps": [
      500
    ],
    "timestamps": [
      "2023-05-19T20:54:01.462408"
    ],
    "values": [
      0.0
    ]
  },
  "return_std": {
    "steps": [
      500
    ],
    "timestamps": [
      "2023-05-19T20:54:01.478102"
    ],
    "values": [
      0.0
    ]
  },
  "test_ep_length_mean": {
    "steps": [
      500
    ],
    "timestamps": [
      "2023-05-19T20:54:26.032334"
    ],
    "values": [
      50.0
    ]
  },
  "test_return_mean": {
    "steps": [
      500
    ],
    "timestamps": [
      "2023-05-19T20:54:26.032334"
    ],
    "values": [
      0.0
    ]
  },
  "test_return_std": {
    "steps": [
      500
    ],
    "timestamps": [
      "2023-05-19T20:54:26.032334"
    ],
    "values": [
      0.0
    ]
  }
}