{
  "advantage_mean": {
    "steps": [
      500
    ],
    "timestamps": [
      "2023-05-21T10:54:19.791377"
    ],
    "values": [
      0.0001579079031944275
    ]
  },
  "agent_grad_norm": {
    "steps": [
      500
    ],
    "timestamps": [
      "2023-05-21T10:54:19.792378"
    ],
    "values": [
      0.06651423871517181
    ]
  },
  "coma_loss": {
    "steps": [
      500
    ],
    "timestamps": [
      "2023-05-21T10:54:19.792378"
    ],
    "values": [
      -0.0023468106519430876
    ]
  },
  "critic_grad_norm": {
    "steps": [
      500
    ],
    "timestamps": [
      "2023-05-21T10:54:19.791377"
    ],
    "values": [
      1.4151254892349243
    ]
  },
  "critic_loss": {
    "steps": [
      500
    ],
    "timestamps": [
      "2023-05-21T10:54:19.791377"
    ],
    "values": [
      0.08602386713027954
    ]
  },
  "ep_length_mean": {
    "steps": [
      500
    ],
    "timestamps": [
      "2023-05-21T10:54:17.313208"
    ],
    "values": [
      50.0
    ]
  },
  "icm_reward_forward_loss": {
    "steps": [
      500
    ],
    "timestamps": [
      "2023-05-21T10:54:19.479947"
    ],
    "values": [
      {}
    ]
  },
  "icm_reward_inverse_loss": {
    "steps": [
      500
    ],
    "timestamps": [
      "2023-05-21T10:54:19.479947"
    ],
    "values": [
      {}
    ]
  },
  "pi_max": {
    "steps": [
      500
    ],
    "timestamps": [
      "2023-05-21T10:54:19.794189"
    ],
    "values": [
      0.2534354705810547
    ]
  },
  "q_taken_mean": {
    "steps": [
      500
    ],
    "timestamps": [
      "2023-05-21T10:54:19.791377"
    ],
    "values": [
      0.1289178466796875
    ]
  },
  "return_mean": {
    "steps": [
      500
    ],
    "timestamps": [
      "2023-05-21T10:54:17.312198"
    ],
    "values": [
      0.0
    ]
  },
  "return_std": {
    "steps": [
      500
    ],
    "timestamps": [
      "2023-05-21T10:54:17.313208"
    ],
    "values": [
      0.0
    ]
  },
  "target_mean": {
    "steps": [
      500
    ],
    "timestamps": [
      "2023-05-21T10:54:19.791377"
    ],
    "values": [
      0.5969462890625
    ]
  },
  "td_error_abs": {
    "steps": [
      500
    ],
    "timestamps": [
      "2023-05-21T10:54:19.791377"
    ],
    "values": [
      0.5004246215820313
    ]
  }
}